openagent/__init__.py
openagent/assistant_agent.py
openagent/base_agent.py
openagent/chatclient.py
openagent/code_interpreter_agent.py
openagent/common_tools.py
openagent/default.py
openagent/ensure_strict_json_schema.py
openagent/exceptions.py
openagent/handoff_workflow.py
openagent/parallel_workflow.py
openagent/react.py
openagent/search_agent.py
openagent/search_engine.py
openagent/sequential_workflow.py
openagent/tools.py
openagent/util.py
openagent/mcp/__init__.py
openagent/mcp/ensure_strict_json_schema.py
openagent/mcp/mcp_client.py
openagent/mcp/mcp_utils.py
openagent/utils/__init__.py
openagent/utils/document_loader.py
openagent/utils/env.py
openagent/utils/formatter.py
openagent/utils/identity.py
openagent/utils/image.py
openagent/utils/logger.py
openagent/utils/multitask.py
openagent/utils/net.py
openagents_sdk-0.1.0.dist-info/licenses/LICENSE
openagents_sdk-0.1.0.dist-info/METADATA
openagents_sdk-0.1.0.dist-info/WHEEL
openagents_sdk-0.1.0.dist-info/top_level.txt
openagents_sdk-0.1.0.dist-info/RECORD
