Metadata-Version: 2.4
Name: openagents-sdk
Version: 0.1.0
Summary: OpenAgent SDK: tools and agents for building AI-driven assistants
Home-page: https://github.com/openagentsfoundation/openagents-sdk/openagent
Author: openagentsfoundation
Author-email: community@openagentsfoundation.org
License: MIT
Requires-Python: >=3.12
License-File: LICENSE
Requires-Dist: aiofiles==24.1.0
Requires-Dist: aiohttp==3.11.11
Requires-Dist: regex==2023.12.25
Requires-Dist: typing_extensions==4.13.2
Requires-Dist: anyio==4.8.0
Requires-Dist: pydantic==2.11.5
Requires-Dist: python-dotenv==1.1.0
Requires-Dist: beautifulsoup4==4.13.4
Requires-Dist: charset_normalizer==3.4.2
Requires-Dist: trafilatura==2.0.0
Requires-Dist: openai==1.82.1
Requires-Dist: mcp==1.6.0
Requires-Dist: pandas==2.2.3
Requires-Dist: PyPDF2==3.0.1
Requires-Dist: python_docx==1.1.2
Requires-Dist: python_pptx==1.0.0
Requires-Dist: playwright==1.49.1
Requires-Dist: numpy==1.26.4
Requires-Dist: sympy==1.13.1
Requires-Dist: pandas==2.2.3
Requires-Dist: matplotlib==3.8.4
Requires-Dist: plotly==5.24.1
Requires-Dist: seaborn==0.13.2
Requires-Dist: scikit-learn==1.4.2
Requires-Dist: statsmodels==0.14.4
Requires-Dist: prophet==1.1.6
Requires-Dist: chainlit==2.5.5
Dynamic: author
Dynamic: author-email
Dynamic: description
Dynamic: description-content-type
Dynamic: home-page
Dynamic: license
Dynamic: license-file
Dynamic: requires-dist
Dynamic: requires-python
Dynamic: summary
